echoes_waveform_models/IMREPhenomAbedi.py
echoes_waveform_models/IMREPhenomBHP.py
echoes_waveform_models/__init__.py
echoes_waveform_models/custom_conditioning.py
echoes_waveform_models/waveform.py
echoes_waveform_models/waveform_utils.py
echoes_waveform_models-0.0.6.dist-info/LICENSE
echoes_waveform_models-0.0.6.dist-info/METADATA
echoes_waveform_models-0.0.6.dist-info/WHEEL
echoes_waveform_models-0.0.6.dist-info/top_level.txt
echoes_waveform_models-0.0.6.dist-info/RECORD
