Metadata-Version: 2.1
Name: echoes_waveform_models
Version: 0.0.6
Summary: A library of GW echoes waveform models
Author-email: Rico Ka Lok Lo <ka-lok.lo@ligo.org>, Nami Uchikata <uchikata@icrr.u-tokyo.ac.jp>
Project-URL: Documentation, https://docs.ligo.org/echoes_template_search/echoes_waveform_models/
Project-URL: Repository, https://git.ligo.org/echoes_template_search/echoes_waveform_models
Requires-Python: >=3.9
License-File: LICENSE
Requires-Dist: numpy
Requires-Dist: scipy
Requires-Dist: matplotlib
Requires-Dist: astropy
Requires-Dist: lalsuite>=7.21
Requires-Dist: gwpy
